fe_openti
