Metadata-Version: 1.1
Name: fe-openti
Version: 0.0.8.1
Summary: this module add changes to fe of openti
Home-page: https://github.com/UrbosSmartCity/fe_openti
Author: Abiezer Sifontes
Author-email: ajsifontes@urbos.io
License: UNKNOWN
Download-URL: https://github.com/RDCH106/urbossmartcity/fe_openti/archive/0.0.6.tar.gz
Platform: UNKNOWN
Classifier: Programming Language :: Python
Classifier: Programming Language :: Python :: 2.7
Classifier: Programming Language :: Python :: 3.3
Classifier: Programming Language :: Python :: 3.4
Classifier: Programming Language :: Python :: 3.5
Classifier: Programming Language :: Python :: 3.6
Classifier: Programming Language :: Python :: 3.7
